Workbook

Sheet Company Overview
A1: Double Materiality Assessment — Tata Steel Limited (Beginner Guide)
A2: Methodology: ESRS-style scoring using Likelihood, Magnitude, Scale, Scope and Irremediability (1-5 scale, scores combine to a 1-25 total)
A4: Company Name | B4: Tata Steel Limited
A5: Sector | B5: Metals & Mining — Iron & Steel Manufacturing
A6: Headquarters | B6: Mumbai, India (part of the Tata Group)
A7: Business Model (simple) | B7: Tata Steel mines iron ore and coal, turns them into steel at large plants in India, the Netherlands and the UK, and sells steel to industries like construction, automotive and infrastructure. It is working to cut carbon emissions by shifting some plants toward electric-arc, scrap-based steelmaking.
A8: Key ESG Risks (industry-specific) | B8: Carbon-heavy steelmaking and climate transition costs; water use and effluents near plants; worker safety in mines and furnaces; land/community impact from mining; air pollution near plants; cybersecurity of plant operations; and business ethics in government contracting and mining licences.
A10: Note
A11: This is a simplified, beginner-level training file. Scores are illustrative (assigned using expert judgement for learning purposes), not Tata Steel's official disclosed figures. Re-check against the latest Tata Steel Integrated Report before using this for a real assessment.

Sheet Scoring Guide
A1: How to Score Each Variable (1 = lowest, 5 = highest)
A3: Likelihood — Used in both the Financial and Impact score. How probable is it that this risk or impact happens (or keeps happening)?
A4: Score | C4: Meaning
A5: 1 | C5: Very unlikely - rare, hypothetical
A6: 2 | C6: Unlikely - could happen, but no clear signal yet
A7: 3 | C7: Possible - plausible within the reporting horizon
A8: 4 | C8: Likely - a clear trend/signal points this way
A9: 5 | C9: Almost certain - already happening or locked in
A11: Magnitude — Used in the Financial score only. If it happens, how big is the financial hit (cost, fine, lost revenue)?
A12: Score | C12: Meaning
A13: 1 | C13: Negligible cost - rounding error on the P&L
A14: 2 | C14: Minor - small, absorbable cost
A15: 3 | C15: Moderate - noticeable line-item impact
A16: 4 | C16: Major - material impact on margins/capital
A17: 5 | C17: Severe - threatens solvency/business model
A19: Scale — Used in the Impact score only. How severe is the harm to people or the environment?
A20: Score | C20: Meaning
A21: 1 | C21: Trivial harm
A22: 2 | C22: Minor harm, easily tolerated
A23: 3 | C23: Moderate harm
A24: 4 | C24: Serious harm
A25: 5 | C25: Grave / catastrophic harm
A27: Scope — Used in the Impact score only. How widespread is the harm - how many people or how much of the environment is affected?
A28: Score | C28: Meaning
A29: 1 | C29: Affects almost no one
A30: 2 | C30: Affects a small local group
A31: 3 | C31: Affects a region / community
A32: 4 | C32: Affects a large population / whole value chain
A33: 5 | C33: Affects a huge population or the whole planet
A35: Irremediability — Used in the Impact score only. How hard is it to undo the damage once it happens?
A36: Score | C36: Meaning
A37: 1 | C37: Instantly and fully reversible
A38: 2 | C38: Reversible with modest effort
A39: 3 | C39: Reversible but slow / costly
A40: 4 | C40: Very hard to reverse
A41: 5 | C41: Permanent / impossible to reverse
A43: Formulas used in this workbook:
A44: Financial Materiality Score = Likelihood x Magnitude (max 25)
A45: Impact Materiality Score = AVERAGE(Scale, Scope, Irremediability) x Likelihood (max 25)
A46: Materiality threshold = 12.5 on each axis (Financial >= 12.5 and/or Impact >= 12.5)

Sheet ESG Topic List
A1: Topic ID | B1: Category (E/S/G) | C1: Topic Name | D1: Plain-English Description
A2: T01 | B2: E | C2: Climate Change (Scope 1 & 2 GHG Emissions) | D2: Carbon emissions from blast-furnace steelmaking, and exposure to carbon pricing/CBAM as regulations tighten.
A3: T02 | B3: E | C3: Water Consumption & Effluents | D3: How much water plants use and how clean the wastewater is when it leaves the plant.
A4: T03 | B4: E | C4: Air Emissions (Dust, SOx, NOx) | D4: Air pollution released from furnaces and coke ovens that can affect nearby communities.
A5: T04 | B5: E | C5: Biodiversity & Mine Land Rehabilitation | D5: Effect of mining on forests and wildlife, and how well mined-out land is restored afterwards.
A6: T05 | B6: E | C6: Energy Management (Coal Dependency) | D6: How much the company still relies on coal for energy versus renewable/cleaner sources.
A7: T06 | B7: S | C7: Occupational Health & Safety | D7: Risk of injury or death to workers in mines, furnaces and heavy-machinery operations.
A8: T07 | B8: S | C8: Employee Diversity & Inclusion | D8: How diverse the workforce is in a traditionally male-dominated heavy industry.
A9: T08 | B9: S | C9: Local Community Development & Displacement | D9: Effect of mining and plant expansion on nearby communities, including land acquisition and resettlement.
A10: T09 | B10: S | C10: Product Quality & Customer Safety | D10: Whether steel products meet safety and quality standards for construction and automotive use.
A11: T10 | B11: G | C11: Cybersecurity Resilience | D11: Risk of a cyberattack disrupting plant operations or exposing company/customer data.
A12: T11 | B12: G | C12: Business Ethics & Anti-Corruption | D12: Risk of bribery or corruption in government contracts and mining-licence approvals.
A13: T12 | B13: G | C13: Board Governance & Climate Oversight | D13: How well the board of directors oversees ESG and climate-related decisions.

Sheet Financial Materiality Scoring
A1: Topic ID | B1: Topic Name | C1: Likelihood (1-5) | D1: Magnitude (1-5) | E1: Financial Materiality Score (Likelihood x Magnitude) | F1: Why this score
A2: T01 | B2: {=INDEX('ESG Topic List'!$C$2:$C$13,MATCH(A2,'ESG Topic List'!$A$2:$A$13,0))} -> Climate Change (Scope 1 & 2 GHG Emissions) | C2: 5 | D2: 5 | E2: =C2*D2 -> 25 | F2: Carbon pricing (EU ETS/CBAM) is already expanding and would hit margins hard - almost certain and severe.
A3: T02 | B3: {=INDEX('ESG Topic List'!$C$2:$C$13,MATCH(A3,'ESG Topic List'!$A$2:$A$13,0))} -> Water Consumption & Effluents | C3: 3 | D3: 3 | E3: =C3*D3 -> 9 | F3: Water-compliance investment is a plausible, moderate line-item cost.
A4: T03 | B4: {=INDEX('ESG Topic List'!$C$2:$C$13,MATCH(A4,'ESG Topic List'!$A$2:$A$13,0))} -> Air Emissions (Dust, SOx, NOx) | C4: 3 | D4: 3 | E4: =C4*D4 -> 9 | F4: Air-quality upgrades and possible fines are a moderate, plausible cost.
A5: T04 | B5: {=INDEX('ESG Topic List'!$C$2:$C$13,MATCH(A5,'ESG Topic List'!$A$2:$A$13,0))} -> Biodiversity & Mine Land Rehabilitation | C5: 2 | D5: 2 | E5: =C5*D5 -> 4 | F5: Fines for a contained biodiversity issue are unlikely and small relative to group finances.
A6: T05 | B6: {=INDEX('ESG Topic List'!$C$2:$C$13,MATCH(A6,'ESG Topic List'!$A$2:$A$13,0))} -> Energy Management (Coal Dependency) | C6: 4 | D6: 4 | E6: =C6*D6 -> 16 | F6: Coal price volatility and phase-down pressure are a likely, major cost driver.
A7: T06 | B7: {=INDEX('ESG Topic List'!$C$2:$C$13,MATCH(A7,'ESG Topic List'!$A$2:$A$13,0))} -> Occupational Health & Safety | C7: 4 | D7: 4 | E7: =C7*D7 -> 16 | F7: Safety incidents are a likely risk and can trigger major penalties and stoppages.
A8: T07 | B8: {=INDEX('ESG Topic List'!$C$2:$C$13,MATCH(A8,'ESG Topic List'!$A$2:$A$13,0))} -> Employee Diversity & Inclusion | C8: 2 | D8: 2 | E8: =C8*D8 -> 4 | F8: DEI gaps mainly affect employer brand; unlikely and minor direct financial cost.
A9: T08 | B9: {=INDEX('ESG Topic List'!$C$2:$C$13,MATCH(A9,'ESG Topic List'!$A$2:$A$13,0))} -> Local Community Development & Displacement | C9: 3 | D9: 3 | E9: =C9*D9 -> 9 | F9: Community disputes can plausibly delay projects at moderate cost.
A10: T09 | B10: {=INDEX('ESG Topic List'!$C$2:$C$13,MATCH(A10,'ESG Topic List'!$A$2:$A$13,0))} -> Product Quality & Customer Safety | C10: 3 | D10: 4 | E10: =C10*D10 -> 12 | F10: Product-quality failures are plausible and could cause major warranty/liability costs.
A11: T10 | B11: {=INDEX('ESG Topic List'!$C$2:$C$13,MATCH(A11,'ESG Topic List'!$A$2:$A$13,0))} -> Cybersecurity Resilience | C11: 5 | D11: 4 | E11: =C11*D11 -> 20 | F11: Cyberattacks are near-certain in any given year and could cause major operational losses.
A12: T11 | B12: {=INDEX('ESG Topic List'!$C$2:$C$13,MATCH(A12,'ESG Topic List'!$A$2:$A$13,0))} -> Business Ethics & Anti-Corruption | C12: 3 | D12: 4 | E12: =C12*D12 -> 12 | F12: A corruption finding is plausible and would carry a major fine/contract-loss risk.
A13: T12 | B13: {=INDEX('ESG Topic List'!$C$2:$C$13,MATCH(A13,'ESG Topic List'!$A$2:$A$13,0))} -> Board Governance & Climate Oversight | C13: 2 | D13: 2 | E13: =C13*D13 -> 4 | F13: Governance gaps are a slow-moving, minor cost to investor confidence.
B14: Average | E14: =AVERAGE(E2:E13) -> 11.666667

Sheet Impact Materiality Scoring
A1: Topic ID | B1: Topic Name | C1: Scale (1-5) | D1: Scope (1-5) | E1: Irremediability (1-5) | F1: Step A: Average(Scale,Scope,Irrem.) | G1: Likelihood (1-5) | H1: Step B: Impact Materiality Score (Average x Likelihood) | I1: Why this score
A2: T01 | B2: {=INDEX('ESG Topic List'!$C$2:$C$13,MATCH(A2,'ESG Topic List'!$A$2:$A$13,0))} -> Climate Change (Scope 1 & 2 GHG Emissions) | C2: 5 | D2: 5 | E2: 4 | F2: =AVERAGE(C2:E2) -> 4.6666667 | G2: 5 | H2: =F2*G2 -> 23.333333 | I2: Emissions drive climate change - grave, widespread, hard to reverse, and happening every year.
A3: T02 | B3: {=INDEX('ESG Topic List'!$C$2:$C$13,MATCH(A3,'ESG Topic List'!$A$2:$A$13,0))} -> Water Consumption & Effluents | C3: 4 | D3: 3 | E3: 3 | F3: =AVERAGE(C3:E3) -> 3.3333333 | G3: 4 | H3: =F3*G3 -> 13.333333 | I3: Water stress harms a regional community; recoverable with investment but not quickly.
A4: T03 | B4: {=INDEX('ESG Topic List'!$C$2:$C$13,MATCH(A4,'ESG Topic List'!$A$2:$A$13,0))} -> Air Emissions (Dust, SOx, NOx) | C4: 4 | D4: 3 | E4: 2 | F4: =AVERAGE(C4:E4) -> 3 | G4: 4 | H4: =F4*G4 -> 12 | I4: Air pollution seriously affects nearby residents but is reversible with abatement tech.
A5: T04 | B5: {=INDEX('ESG Topic List'!$C$2:$C$13,MATCH(A5,'ESG Topic List'!$A$2:$A$13,0))} -> Biodiversity & Mine Land Rehabilitation | C5: 5 | D5: 3 | E5: 5 | F5: =AVERAGE(C5:E5) -> 4.3333333 | G5: 4 | H5: =F5*G5 -> 17.333333 | I5: Mining can permanently damage local ecosystems even though it is not group-wide in scope.
A6: T05 | B6: {=INDEX('ESG Topic List'!$C$2:$C$13,MATCH(A6,'ESG Topic List'!$A$2:$A$13,0))} -> Energy Management (Coal Dependency) | C6: 3 | D6: 3 | E6: 2 | F6: =AVERAGE(C6:E6) -> 2.6666667 | G6: 3 | H6: =F6*G6 -> 8 | I6: Coal dependency has a moderate, regional climate contribution that is fairly reversible over time.
A7: T06 | B7: {=INDEX('ESG Topic List'!$C$2:$C$13,MATCH(A7,'ESG Topic List'!$A$2:$A$13,0))} -> Occupational Health & Safety | C7: 5 | D7: 3 | E7: 4 | F7: =AVERAGE(C7:E7) -> 4 | G7: 4 | H7: =F7*G7 -> 16 | I7: A fatality/injury is grave for the worker and hard to reverse; safety incidents are a likely risk.
A8: T07 | B8: {=INDEX('ESG Topic List'!$C$2:$C$13,MATCH(A8,'ESG Topic List'!$A$2:$A$13,0))} -> Employee Diversity & Inclusion | C8: 2 | D8: 2 | E8: 1 | F8: =AVERAGE(C8:E8) -> 1.6666667 | G8: 3 | H8: =F8*G8 -> 5 | I8: Underrepresentation is a real but low-severity, easily reversible issue.
A9: T08 | B9: {=INDEX('ESG Topic List'!$C$2:$C$13,MATCH(A9,'ESG Topic List'!$A$2:$A$13,0))} -> Local Community Development & Displacement | C9: 4 | D9: 3 | E9: 4 | F9: =AVERAGE(C9:E9) -> 3.6666667 | G9: 4 | H9: =F9*G9 -> 14.666667 | I9: Displacement causes serious, regional harm that is hard - though not impossible - to remedy.
A10: T09 | B10: {=INDEX('ESG Topic List'!$C$2:$C$13,MATCH(A10,'ESG Topic List'!$A$2:$A$13,0))} -> Product Quality & Customer Safety | C10: 3 | D10: 3 | E10: 2 | F10: =AVERAGE(C10:E10) -> 2.6666667 | G10: 3 | H10: =F10*G10 -> 8 | I10: A product failure could seriously affect a limited set of customers, and is fixable via recalls/QA.
A11: T10 | B11: {=INDEX('ESG Topic List'!$C$2:$C$13,MATCH(A11,'ESG Topic List'!$A$2:$A$13,0))} -> Cybersecurity Resilience | C11: 2 | D11: 2 | E11: 2 | F11: =AVERAGE(C11:E11) -> 2 | G11: 3 | H11: =F11*G11 -> 6 | I11: A breach mainly inconveniences a limited set of customers and can be remediated.
A12: T11 | B12: {=INDEX('ESG Topic List'!$C$2:$C$13,MATCH(A12,'ESG Topic List'!$A$2:$A$13,0))} -> Business Ethics & Anti-Corruption | C12: 3 | D12: 2 | E12: 2 | F12: =AVERAGE(C12:E12) -> 2.3333333 | G12: 3 | H12: =F12*G12 -> 7 | I12: A corruption incident causes moderate, containable reputational/social harm.
A13: T12 | B13: {=INDEX('ESG Topic List'!$C$2:$C$13,MATCH(A13,'ESG Topic List'!$A$2:$A$13,0))} -> Board Governance & Climate Oversight | C13: 2 | D13: 2 | E13: 1 | F13: =AVERAGE(C13:E13) -> 1.6666667 | G13: 2 | H13: =F13*G13 -> 3.3333333 | I13: Weak board oversight is a low-severity, reversible structural gap.
B14: Average | H14: =AVERAGE(H2:H13) -> 11.166667

Sheet Double Materiality Matrix
A1: Topic ID | B1: Topic Name | C1: Financial Score (X) | D1: Impact Score (Y) | E1: Materiality Category
A2: T01 | B2: {=INDEX('ESG Topic List'!$C$2:$C$13,MATCH(A2,'ESG Topic List'!$A$2:$A$13,0))} -> Climate Change (Scope 1 & 2 GHG Emissions) | C2: {=INDEX('Financial Materiality Scoring'!$E$2:$E$13,MATCH(A2,'Financial Materiality Scoring'!$A$2:$A$13,0))} -> 25 | D2: {=INDEX('Impact Materiality Scoring'!$H$2:$H$13,MATCH(A2,'Impact Materiality Scoring'!$A$2:$A$13,0))} -> 23.333333 | E2: =IF(AND(C2>=12.5,D2>=12.5),"Double Material",IF(AND(D2>=12.5,C2<12.5),"Impact-Only Material",IF(AND(C2>=12.5,D2<12.5),"Financial-Only Material","Not Material"))) -> Double Material
A3: T02 | B3: {=INDEX('ESG Topic List'!$C$2:$C$13,MATCH(A3,'ESG Topic List'!$A$2:$A$13,0))} -> Water Consumption & Effluents | C3: {=INDEX('Financial Materiality Scoring'!$E$2:$E$13,MATCH(A3,'Financial Materiality Scoring'!$A$2:$A$13,0))} -> 9 | D3: {=INDEX('Impact Materiality Scoring'!$H$2:$H$13,MATCH(A3,'Impact Materiality Scoring'!$A$2:$A$13,0))} -> 13.333333 | E3: =IF(AND(C3>=12.5,D3>=12.5),"Double Material",IF(AND(D3>=12.5,C3<12.5),"Impact-Only Material",IF(AND(C3>=12.5,D3<12.5),"Financial-Only Material","Not Material"))) -> Impact-Only Material
A4: T03 | B4: {=INDEX('ESG Topic List'!$C$2:$C$13,MATCH(A4,'ESG Topic List'!$A$2:$A$13,0))} -> Air Emissions (Dust, SOx, NOx) | C4: {=INDEX('Financial Materiality Scoring'!$E$2:$E$13,MATCH(A4,'Financial Materiality Scoring'!$A$2:$A$13,0))} -> 9 | D4: {=INDEX('Impact Materiality Scoring'!$H$2:$H$13,MATCH(A4,'Impact Materiality Scoring'!$A$2:$A$13,0))} -> 12 | E4: =IF(AND(C4>=12.5,D4>=12.5),"Double Material",IF(AND(D4>=12.5,C4<12.5),"Impact-Only Material",IF(AND(C4>=12.5,D4<12.5),"Financial-Only Material","Not Material"))) -> Not Material
A5: T04 | B5: {=INDEX('ESG Topic List'!$C$2:$C$13,MATCH(A5,'ESG Topic List'!$A$2:$A$13,0))} -> Biodiversity & Mine Land Rehabilitation | C5: {=INDEX('Financial Materiality Scoring'!$E$2:$E$13,MATCH(A5,'Financial Materiality Scoring'!$A$2:$A$13,0))} -> 4 | D5: {=INDEX('Impact Materiality Scoring'!$H$2:$H$13,MATCH(A5,'Impact Materiality Scoring'!$A$2:$A$13,0))} -> 17.333333 | E5: =IF(AND(C5>=12.5,D5>=12.5),"Double Material",IF(AND(D5>=12.5,C5<12.5),"Impact-Only Material",IF(AND(C5>=12.5,D5<12.5),"Financial-Only Material","Not Material"))) -> Impact-Only Material
A6: T05 | B6: {=INDEX('ESG Topic List'!$C$2:$C$13,MATCH(A6,'ESG Topic List'!$A$2:$A$13,0))} -> Energy Management (Coal Dependency) | C6: {=INDEX('Financial Materiality Scoring'!$E$2:$E$13,MATCH(A6,'Financial Materiality Scoring'!$A$2:$A$13,0))} -> 16 | D6: {=INDEX('Impact Materiality Scoring'!$H$2:$H$13,MATCH(A6,'Impact Materiality Scoring'!$A$2:$A$13,0))} -> 8 | E6: =IF(AND(C6>=12.5,D6>=12.5),"Double Material",IF(AND(D6>=12.5,C6<12.5),"Impact-Only Material",IF(AND(C6>=12.5,D6<12.5),"Financial-Only Material","Not Material"))) -> Financial-Only Material
A7: T06 | B7: {=INDEX('ESG Topic List'!$C$2:$C$13,MATCH(A7,'ESG Topic List'!$A$2:$A$13,0))} -> Occupational Health & Safety | C7: {=INDEX('Financial Materiality Scoring'!$E$2:$E$13,MATCH(A7,'Financial Materiality Scoring'!$A$2:$A$13,0))} -> 16 | D7: {=INDEX('Impact Materiality Scoring'!$H$2:$H$13,MATCH(A7,'Impact Materiality Scoring'!$A$2:$A$13,0))} -> 16 | E7: =IF(AND(C7>=12.5,D7>=12.5),"Double Material",IF(AND(D7>=12.5,C7<12.5),"Impact-Only Material",IF(AND(C7>=12.5,D7<12.5),"Financial-Only Material","Not Material"))) -> Double Material
A8: T07 | B8: {=INDEX('ESG Topic List'!$C$2:$C$13,MATCH(A8,'ESG Topic List'!$A$2:$A$13,0))} -> Employee Diversity & Inclusion | C8: {=INDEX('Financial Materiality Scoring'!$E$2:$E$13,MATCH(A8,'Financial Materiality Scoring'!$A$2:$A$13,0))} -> 4 | D8: {=INDEX('Impact Materiality Scoring'!$H$2:$H$13,MATCH(A8,'Impact Materiality Scoring'!$A$2:$A$13,0))} -> 5 | E8: =IF(AND(C8>=12.5,D8>=12.5),"Double Material",IF(AND(D8>=12.5,C8<12.5),"Impact-Only Material",IF(AND(C8>=12.5,D8<12.5),"Financial-Only Material","Not Material"))) -> Not Material
A9: T08 | B9: {=INDEX('ESG Topic List'!$C$2:$C$13,MATCH(A9,'ESG Topic List'!$A$2:$A$13,0))} -> Local Community Development & Displacement | C9: {=INDEX('Financial Materiality Scoring'!$E$2:$E$13,MATCH(A9,'Financial Materiality Scoring'!$A$2:$A$13,0))} -> 9 | D9: {=INDEX('Impact Materiality Scoring'!$H$2:$H$13,MATCH(A9,'Impact Materiality Scoring'!$A$2:$A$13,0))} -> 14.666667 | E9: =IF(AND(C9>=12.5,D9>=12.5),"Double Material",IF(AND(D9>=12.5,C9<12.5),"Impact-Only Material",IF(AND(C9>=12.5,D9<12.5),"Financial-Only Material","Not Material"))) -> Impact-Only Material
A10: T09 | B10: {=INDEX('ESG Topic List'!$C$2:$C$13,MATCH(A10,'ESG Topic List'!$A$2:$A$13,0))} -> Product Quality & Customer Safety | C10: {=INDEX('Financial Materiality Scoring'!$E$2:$E$13,MATCH(A10,'Financial Materiality Scoring'!$A$2:$A$13,0))} -> 12 | D10: {=INDEX('Impact Materiality Scoring'!$H$2:$H$13,MATCH(A10,'Impact Materiality Scoring'!$A$2:$A$13,0))} -> 8 | E10: =IF(AND(C10>=12.5,D10>=12.5),"Double Material",IF(AND(D10>=12.5,C10<12.5),"Impact-Only Material",IF(AND(C10>=12.5,D10<12.5),"Financial-Only Material","Not Material"))) -> Not Material
A11: T10 | B11: {=INDEX('ESG Topic List'!$C$2:$C$13,MATCH(A11,'ESG Topic List'!$A$2:$A$13,0))} -> Cybersecurity Resilience | C11: {=INDEX('Financial Materiality Scoring'!$E$2:$E$13,MATCH(A11,'Financial Materiality Scoring'!$A$2:$A$13,0))} -> 20 | D11: {=INDEX('Impact Materiality Scoring'!$H$2:$H$13,MATCH(A11,'Impact Materiality Scoring'!$A$2:$A$13,0))} -> 6 | E11: =IF(AND(C11>=12.5,D11>=12.5),"Double Material",IF(AND(D11>=12.5,C11<12.5),"Impact-Only Material",IF(AND(C11>=12.5,D11<12.5),"Financial-Only Material","Not Material"))) -> Financial-Only Material
A12: T11 | B12: {=INDEX('ESG Topic List'!$C$2:$C$13,MATCH(A12,'ESG Topic List'!$A$2:$A$13,0))} -> Business Ethics & Anti-Corruption | C12: {=INDEX('Financial Materiality Scoring'!$E$2:$E$13,MATCH(A12,'Financial Materiality Scoring'!$A$2:$A$13,0))} -> 12 | D12: {=INDEX('Impact Materiality Scoring'!$H$2:$H$13,MATCH(A12,'Impact Materiality Scoring'!$A$2:$A$13,0))} -> 7 | E12: =IF(AND(C12>=12.5,D12>=12.5),"Double Material",IF(AND(D12>=12.5,C12<12.5),"Impact-Only Material",IF(AND(C12>=12.5,D12<12.5),"Financial-Only Material","Not Material"))) -> Not Material
A13: T12 | B13: {=INDEX('ESG Topic List'!$C$2:$C$13,MATCH(A13,'ESG Topic List'!$A$2:$A$13,0))} -> Board Governance & Climate Oversight | C13: {=INDEX('Financial Materiality Scoring'!$E$2:$E$13,MATCH(A13,'Financial Materiality Scoring'!$A$2:$A$13,0))} -> 4 | D13: {=INDEX('Impact Materiality Scoring'!$H$2:$H$13,MATCH(A13,'Impact Materiality Scoring'!$A$2:$A$13,0))} -> 3.3333333 | E13: =IF(AND(C13>=12.5,D13>=12.5),"Double Material",IF(AND(D13>=12.5,C13<12.5),"Impact-Only Material",IF(AND(C13>=12.5,D13<12.5),"Financial-Only Material","Not Material"))) -> Not Material
A15: Category Logic (threshold = 12.5 on each axis, scores run 1-25)
A16: Double Material | B16: Financial Score >= 12.5 AND Impact Score >= 12.5
A17: Impact-Only Material | B17: Impact Score >= 12.5 AND Financial Score < 12.5
A18: Financial-Only Material | B18: Financial Score >= 12.5 AND Impact Score < 12.5
A19: Not Material | B19: Financial Score < 12.5 AND Impact Score < 12.5

Sheet Matrix Chart
A1: Double Materiality Matrix - Scatter Data
A2: Topic Name | B2: Financial Score (X) | C2: Impact Score (Y) | D2: Threshold X=12.5 | E2: Threshold Y=12.5
A3: ='Double Materiality Matrix'!B2 -> Climate Change (Scope 1 & 2 GHG Emissions) | B3: ='Double Materiality Matrix'!C2 -> 25 | C3: ='Double Materiality Matrix'!D2 -> 23.333333
A4: ='Double Materiality Matrix'!B3 -> Water Consumption & Effluents | B4: ='Double Materiality Matrix'!C3 -> 9 | C4: ='Double Materiality Matrix'!D3 -> 13.333333
A5: ='Double Materiality Matrix'!B4 -> Air Emissions (Dust, SOx, NOx) | B5: ='Double Materiality Matrix'!C4 -> 9 | C5: ='Double Materiality Matrix'!D4 -> 12
A6: ='Double Materiality Matrix'!B5 -> Biodiversity & Mine Land Rehabilitation | B6: ='Double Materiality Matrix'!C5 -> 4 | C6: ='Double Materiality Matrix'!D5 -> 17.333333
A7: ='Double Materiality Matrix'!B6 -> Energy Management (Coal Dependency) | B7: ='Double Materiality Matrix'!C6 -> 16 | C7: ='Double Materiality Matrix'!D6 -> 8
A8: ='Double Materiality Matrix'!B7 -> Occupational Health & Safety | B8: ='Double Materiality Matrix'!C7 -> 16 | C8: ='Double Materiality Matrix'!D7 -> 16
A9: ='Double Materiality Matrix'!B8 -> Employee Diversity & Inclusion | B9: ='Double Materiality Matrix'!C8 -> 4 | C9: ='Double Materiality Matrix'!D8 -> 5
A10: ='Double Materiality Matrix'!B9 -> Local Community Development & Displacement | B10: ='Double Materiality Matrix'!C9 -> 9 | C10: ='Double Materiality Matrix'!D9 -> 14.666667
A11: ='Double Materiality Matrix'!B10 -> Product Quality & Customer Safety | B11: ='Double Materiality Matrix'!C10 -> 12 | C11: ='Double Materiality Matrix'!D10 -> 8
A12: ='Double Materiality Matrix'!B11 -> Cybersecurity Resilience | B12: ='Double Materiality Matrix'!C11 -> 20 | C12: ='Double Materiality Matrix'!D11 -> 6
A13: ='Double Materiality Matrix'!B12 -> Business Ethics & Anti-Corruption | B13: ='Double Materiality Matrix'!C12 -> 12 | C13: ='Double Materiality Matrix'!D12 -> 7
A14: ='Double Materiality Matrix'!B13 -> Board Governance & Climate Oversight | B14: ='Double Materiality Matrix'!C13 -> 4 | C14: ='Double Materiality Matrix'!D13 -> 3.3333333
A15: Threshold X=12.5 (Start) | B15: 12.5 | D15: 0
A16: Threshold X=12.5 (End) | B16: 12.5 | D16: 25
A17: Threshold Y=12.5 (Start) | B17: 0 | E17: 12.5
A18: Threshold Y=12.5 (End) | B18: 25 | E18: 12.5
G23: Double Materiality Matrix — Quadrant Reference Guide (Threshold = 12.5)
G24: Quadrant II: Impact-Only Material | J24: Quadrant I: Double Material (Highest Priority)
G25: Impact Score ≥ 12.5 | Financial Score < 12.5 | J25: Financial Score ≥ 12.5 | Impact Score ≥ 12.5
G26: ="Topics: " & COUNTIFS(C3:C14, ">=12.5", B3:B14, "<12.5") & " (Water, Biodiversity, Community)" -> Topics: 3 (Water, Biodiversity, Community) | J26: ="Topics: " & COUNTIFS(B3:B14, ">=12.5", C3:C14, ">=12.5") & " (Climate Change, Health & Safety)" -> Topics: 2 (Climate Change, Health & Safety)
G27: Key Focus: Environmental & Social impacts | J27: Key Focus: Strategic ESG & financial drivers
G28: Quadrant III: Not Material / Low Priority | J28: Quadrant IV: Financial-Only Material
G29: Financial Score < 12.5 | Impact Score < 12.5 | J29: Financial Score ≥ 12.5 | Impact Score < 12.5
G30: ="Topics: " & COUNTIFS(B3:B14, "<12.5", C3:C14, "<12.5") & " (Air, D&I, Ethics, Gov, Product)" -> Topics: 5 (Air, D&I, Ethics, Gov, Product) | J30: ="Topics: " & COUNTIFS(B3:B14, ">=12.5", C3:C14, "<12.5") & " (Energy Mgmt, Cybersecurity)" -> Topics: 2 (Energy Mgmt, Cybersecurity)
G31: Key Focus: Baseline monitoring & compliance | J31: Key Focus: Operational risk & capital allocation

Sheet Dashboard
A1: Executive Dashboard — Tata Steel Double Materiality
A3: Metric | B3: Value | C3: Formula Used
A4: Total ESG Topics Assessed | B4: =COUNTA('ESG Topic List'!A2:A13) -> 12 | C4: COUNTA(ESG Topic List!A:A)
A5: Count: Double Material | B5: =COUNTIF('Double Materiality Matrix'!E2:E13,"Double Material") -> 2 | C5: COUNTIF(...,"Double Material")
A6: Count: Impact-Only Material | B6: =COUNTIF('Double Materiality Matrix'!E2:E13,"Impact-Only Material") -> 3 | C6: COUNTIF(...,"Impact-Only Material")
A7: Count: Financial-Only Material | B7: =COUNTIF('Double Materiality Matrix'!E2:E13,"Financial-Only Material") -> 2 | C7: COUNTIF(...,"Financial-Only Material")
A8: Count: Not Material | B8: =COUNTIF('Double Materiality Matrix'!E2:E13,"Not Material") -> 5 | C8: COUNTIF(...,"Not Material")
A9: Average Financial Score | B9: =AVERAGE('Double Materiality Matrix'!C2:C13) -> 11.666667 | C9: AVERAGE(Double Materiality Matrix!C:C)
A10: Average Impact Score | B10: =AVERAGE('Double Materiality Matrix'!D2:D13) -> 11.166667 | C10: AVERAGE(Double Materiality Matrix!D:D)
A11: Highest Financial Score | B11: =MAX('Double Materiality Matrix'!C2:C13) -> 25 | C11: MAX(Double Materiality Matrix!C:C)
A12: Highest Impact Score | B12: =MAX('Double Materiality Matrix'!D2:D13) -> 23.333333 | C12: MAX(Double Materiality Matrix!D:D)
A14: Category Distribution
A15: Category | B15: Count
A16: Double Material | B16: =COUNTIF('Double Materiality Matrix'!E2:E13,A16) -> 2
A17: Impact-Only Material | B17: =COUNTIF('Double Materiality Matrix'!E2:E13,A17) -> 3
A18: Financial-Only Material | B18: =COUNTIF('Double Materiality Matrix'!E2:E13,A18) -> 2
A19: Not Material | B19: =COUNTIF('Double Materiality Matrix'!E2:E13,A19) -> 5
